rest_easy/__init__.py
rest_easy/api.py
rest_easy/version.py
rest_easy/specification/__init__.py
rest_easy/specification/core.py
rest_easy/specification/fields.py
rest_easy/specification/marshalling.py
rest_easy-0.0.1.dev0.dist-info/DESCRIPTION.rst
rest_easy-0.0.1.dev0.dist-info/METADATA
rest_easy-0.0.1.dev0.dist-info/RECORD
rest_easy-0.0.1.dev0.dist-info/WHEEL
rest_easy-0.0.1.dev0.dist-info/metadata.json
rest_easy-0.0.1.dev0.dist-info/top_level.txt
tests/__init__.py
tests/test_api.py
tests/test_specification.py
tests/test_version.py
