Metadata-Version: 2.0
Name: rest-easy
Version: 0.0.1.dev0
Summary: Makes ReST Easy - Work in Progress
Home-page: https://www.github.com/mplanchard/rest-easy
Author: Matthew Planchard
Author-email: msplanchard@gmail.com
License: UNKNOWN
Platform: UNKNOWN
Classifier: Development Status :: 1 - Planning
Classifier: Intended Audience :: Developers
Classifier: License :: OSI Approved :: MIT License
Classifier: Natural Language :: English
Classifier: Operating System :: POSIX :: Linux
Classifier: Programming Language :: Python
Classifier: Programming Language :: Python :: 3 :: Only
Requires-Dist: flasgger
Requires-Dist: flask
Requires-Dist: marshmallow
Requires-Dist: six
